mongodex/__init__.py
mongodex/docs.py
mongodex/helpers.py
mongodex/main.py
mongodex-0.0.1.dist-info/METADATA
mongodex-0.0.1.dist-info/WHEEL
mongodex-0.0.1.dist-info/licenses/LICENSE
mongodex-0.0.1.dist-info/RECORD
