Metadata-Version: 2.1
Name: mongodex
Version: 0.0.1
Summary: MongoDB Index migration tool
Project-URL: Homepage, https://github.com/pinio/mongodex
Project-URL: Bug Tracker, https://github.com/pinio/mongodex/issues
Author-email: Danilo Martins <mawkee@gmail.com>, Evandro Arruda <ecarruda@gmail.com>, Murilo Viana <murilo.vianamo@gmail.com>
License: MIT License
Classifier: License :: OSI Approved :: MIT License
Classifier: Operating System :: OS Independent
Classifier: Programming Language :: Python :: 3
Classifier: Topic :: Database
Requires-Python: >=3.7
Requires-Dist: loguru
Requires-Dist: pymongo
